tatrapayplus/__init__.py
tatrapayplus/client.py
tatrapayplus/enums.py
tatrapayplus/errors.py
tatrapayplus/helpers.py
tatrapayplus/py.typed
tatrapayplus/types.py
tatrapayplus/models/__init__.py
tatrapayplus/models/account_reference.py
tatrapayplus/models/address.py
tatrapayplus/models/amount.py
tatrapayplus/models/amount_range_rule.py
tatrapayplus/models/appearance_logo_request.py
tatrapayplus/models/appearance_request.py
tatrapayplus/models/appearance_request_theme.py
tatrapayplus/models/apple_pay_token.py
tatrapayplus/models/apple_pay_token_token.py
tatrapayplus/models/apple_pay_token_token_header.py
tatrapayplus/models/available_payment_method.py
tatrapayplus/models/available_payment_method_reason_code_method_availability.py
tatrapayplus/models/bank_transfer.py
tatrapayplus/models/bank_transfer_status.py
tatrapayplus/models/base_payment.py
tatrapayplus/models/basic_calculation_request.py
tatrapayplus/models/basic_calculation_request_payment_method.py
tatrapayplus/models/basic_calculation_response_item.py
tatrapayplus/models/capacity_info.py
tatrapayplus/models/card_detail.py
tatrapayplus/models/card_detail_card_pay_lang_override.py
tatrapayplus/models/card_pay_amount.py
tatrapayplus/models/card_pay_status.py
tatrapayplus/models/card_pay_status_structure.py
tatrapayplus/models/card_pay_status_structure_comfort_pay.py
tatrapayplus/models/card_pay_update_instruction.py
tatrapayplus/models/card_pay_update_instruction_operation_type.py
tatrapayplus/models/color_attribute.py
tatrapayplus/models/comfort_pay.py
tatrapayplus/models/comfort_pay_status.py
tatrapayplus/models/direct_transaction_data.py
tatrapayplus/models/direct_transaction_status.py
tatrapayplus/models/direct_transaction_task_status_response.py
tatrapayplus/models/direct_transaction_tds_data.py
tatrapayplus/models/field_400_error_body.py
tatrapayplus/models/field_400_error_body_error_code.py
tatrapayplus/models/field_40x_error_body.py
tatrapayplus/models/field_40x_error_body_error_code.py
tatrapayplus_python-1.0.1.dist-info/METADATA
tatrapayplus_python-1.0.1.dist-info/WHEEL
tatrapayplus_python-1.0.1.dist-info/licenses/LICENSE
tatrapayplus_python-1.0.1.dist-info/RECORD
